CHANGES.txt
README.txt
bootstrap.py
buildout.cfg
setup.py
src/z3c/__init__.py
src/z3c.setuptools_mercurial.egg-info/PKG-INFO
src/z3c.setuptools_mercurial.egg-info/SOURCES.txt
src/z3c.setuptools_mercurial.egg-info/dependency_links.txt
src/z3c.setuptools_mercurial.egg-info/entry_points.txt
src/z3c.setuptools_mercurial.egg-info/namespace_packages.txt
src/z3c.setuptools_mercurial.egg-info/not-zip-safe
src/z3c.setuptools_mercurial.egg-info/requires.txt
src/z3c.setuptools_mercurial.egg-info/top_level.txt
src/z3c/setuptools_mercurial/README.txt
src/z3c/setuptools_mercurial/__init__.py
src/z3c/setuptools_mercurial/finder.py
src/z3c/setuptools_mercurial/tests.py