Metadata-Version: 1.0
Name: z3c.setuptools-mercurial
Version: 1.1.1
Summary: Mercurial File Finder Plugin for Setuptools
Home-page: http://pypi.python.org/pypi/z3c.setuptools_mercurial
Author: Stephan Richter and the Zope Community
Author-email: zope-dev@zope.org
License: ZPL 2.1
Keywords: setuptools mercurial distribution
Platform: UNKNOWN
Classifier: Development Status :: 4 - Beta
Classifier: Environment :: Web Environment
Classifier: Intended Audience :: Developers
Classifier: License :: OSI Approved :: Zope Public License
Classifier: Programming Language :: Python
Classifier: Natural Language :: English
Classifier: Operating System :: OS Independent
Classifier: Topic :: Software Development :: Version Control
Classifier: Framework :: Setuptools Plugin
